package com.google.android.gms.common.internal;

import com.google.android.gms.common.annotation.KeepForSdk;
import com.google.android.gms.common.util.VisibleForTesting;
import java.util.concurrent.ConcurrentHashMap;

@Deprecated
@KeepForSdk
public class LibraryVersion
{
  private static final GmsLogger zza = new GmsLogger("LibraryVersion", "");
  private static LibraryVersion zzb = new LibraryVersion();
  private ConcurrentHashMap zzc = new ConcurrentHashMap();
  
  @VisibleForTesting
  protected LibraryVersion() {}
  
  @KeepForSdk
  public static LibraryVersion getInstance()
  {
    return zzb;
  }
  
  /* Error */
  @Deprecated
  @KeepForSdk
  public String getVersion(String paramString)
  {
    // Byte code:
    //   0: aload_1
    //   1: ldc 47
    //   3: invokestatic 53	com/google/android/gms/common/internal/Preconditions:checkNotEmpty	(Ljava/lang/String;Ljava/lang/Object;)Ljava/lang/String;
    //   6: pop
    //   7: aload_0
    //   8: getfield 38	com/google/android/gms/common/internal/LibraryVersion:zzc	Ljava/util/concurrent/ConcurrentHashMap;
    //   11: aload_1
    //   12: invokevirtual 57	java/util/concurrent/ConcurrentHashMap:containsKey	(Ljava/lang/Object;)Z
    //   15: ifeq +15 -> 30
    //   18: aload_0
    //   19: getfield 38	com/google/android/gms/common/internal/LibraryVersion:zzc	Ljava/util/concurrent/ConcurrentHashMap;
    //   22: aload_1
    //   23: invokevirtual 61	java/util/concurrent/ConcurrentHashMap:get	(Ljava/lang/Object;)Ljava/lang/Object;
    //   26: checkcast 63	java/lang/String
    //   29: areturn
    //   30: new 65	java/util/Properties
    //   33: dup
    //   34: invokespecial 66	java/util/Properties:<init>	()V
    //   37: astore 7
    //   39: aconst_null
    //   40: astore 5
    //   42: aconst_null
    //   43: astore_2
    //   44: aconst_null
    //   45: astore 6
    //   47: aconst_null
    //   48: astore_3
    //   49: ldc 2
    //   51: ldc 68
    //   53: iconst_1
    //   54: anewarray 4	java/lang/Object
    //   57: dup
    //   58: iconst_0
    //   59: aload_1
    //   60: aastore
    //   61: invokestatic 72	java/lang/String:format	(Ljava/lang/String;[Ljava/lang/Object;)Ljava/lang/String;
    //   64: invokevirtual 78	java/lang/Class:getResourceAsStream	(Ljava/lang/String;)Ljava/io/InputStream;
    //   67: astore 4
    //   69: aload 4
    //   71: ifnull +88 -> 159
    //   74: aload 5
    //   76: astore_2
    //   77: aload 7
    //   79: aload 4
    //   81: invokevirtual 82	java/util/Properties:load	(Ljava/io/InputStream;)V
    //   84: aload 5
    //   86: astore_2
    //   87: aload 7
    //   89: ldc 84
    //   91: aconst_null
    //   92: invokevirtual 88	java/util/Properties:getProperty	(Ljava/lang/String;Ljava/lang/String;)Ljava/lang/String;
    //   95: astore_3
    //   96: aload_3
    //   97: astore_2
    //   98: getstatic 26	com/google/android/gms/common/internal/LibraryVersion:zza	Lcom/google/android/gms/common/internal/GmsLogger;
    //   101: astore 5
    //   103: aload_3
    //   104: astore_2
    //   105: new 90	java/lang/StringBuilder
    //   108: dup
    //   109: invokespecial 91	java/lang/StringBuilder:<init>	()V
    //   112: astore 6
    //   114: aload_3
    //   115: astore_2
    //   116: aload 6
    //   118: aload_1
    //   119: invokevirtual 95	java/lang/StringBuilder:append	(Ljava/lang/String;)Ljava/lang/StringBuilder;
    //   122: pop
    //   123: aload_3
    //   124: astore_2
    //   125: aload 6
    //   127: ldc 97
    //   129: invokevirtual 95	java/lang/StringBuilder:append	(Ljava/lang/String;)Ljava/lang/StringBuilder;
    //   132: pop
    //   133: aload_3
    //   134: astore_2
    //   135: aload 6
    //   137: aload_3
    //   138: invokevirtual 95	java/lang/StringBuilder:append	(Ljava/lang/String;)Ljava/lang/StringBuilder;
    //   141: pop
    //   142: aload_3
    //   143: astore_2
    //   144: aload 5
    //   146: ldc 18
    //   148: aload 6
    //   150: invokevirtual 101	java/lang/StringBuilder:toString	()Ljava/lang/String;
    //   153: invokevirtual 104	com/google/android/gms/common/internal/GmsLogger:v	(Ljava/lang/String;Ljava/lang/String;)V
    //   156: goto +59 -> 215
    //   159: aload 5
    //   161: astore_2
    //   162: getstatic 26	com/google/android/gms/common/internal/LibraryVersion:zza	Lcom/google/android/gms/common/internal/GmsLogger;
    //   165: astore 6
    //   167: aload 5
    //   169: astore_2
    //   170: new 90	java/lang/StringBuilder
    //   173: dup
    //   174: invokespecial 91	java/lang/StringBuilder:<init>	()V
    //   177: astore 7
    //   179: aload 5
    //   181: astore_2
    //   182: aload 7
    //   184: ldc 106
    //   186: invokevirtual 95	java/lang/StringBuilder:append	(Ljava/lang/String;)Ljava/lang/StringBuilder;
    //   189: pop
    //   190: aload 5
    //   192: astore_2
    //   193: aload 7
    //   195: aload_1
    //   196: invokevirtual 95	java/lang/StringBuilder:append	(Ljava/lang/String;)Ljava/lang/StringBuilder;
    //   199: pop
    //   200: aload 5
    //   202: astore_2
    //   203: aload 6
    //   205: ldc 18
    //   207: aload 7
    //   209: invokevirtual 101	java/lang/StringBuilder:toString	()Ljava/lang/String;
    //   212: invokevirtual 109	com/google/android/gms/common/internal/GmsLogger:w	(Ljava/lang/String;Ljava/lang/String;)V
    //   215: aload_3
    //   216: astore_2
    //   217: aload 4
    //   219: ifnull +109 -> 328
    //   222: aload 4
    //   224: invokestatic 115	com/google/android/gms/common/util/IOUtils:closeQuietly	(Ljava/io/Closeable;)V
    //   227: aload_3
    //   228: astore_2
    //   229: goto +99 -> 328
    //   232: astore_1
    //   233: aload 4
    //   235: astore_2
    //   236: goto +123 -> 359
    //   239: astore 5
    //   241: aload_2
    //   242: astore_3
    //   243: goto +15 -> 258
    //   246: astore_1
    //   247: goto +112 -> 359
    //   250: astore 5
    //   252: aconst_null
    //   253: astore_3
    //   254: aload 6
    //   256: astore 4
    //   258: aload 4
    //   260: astore_2
    //   261: getstatic 26	com/google/android/gms/common/internal/LibraryVersion:zza	Lcom/google/android/gms/common/internal/GmsLogger;
    //   264: astore 6
    //   266: aload 4
    //   268: astore_2
    //   269: new 90	java/lang/StringBuilder
    //   272: dup
    //   273: invokespecial 91	java/lang/StringBuilder:<init>	()V
    //   276: astore 7
    //   278: aload 4
    //   280: astore_2
    //   281: aload 7
    //   283: ldc 106
    //   285: invokevirtual 95	java/lang/StringBuilder:append	(Ljava/lang/String;)Ljava/lang/StringBuilder;
    //   288: pop
    //   289: aload 4
    //   291: astore_2
    //   292: aload 7
    //   294: aload_1
    //   295: invokevirtual 95	java/lang/StringBuilder:append	(Ljava/lang/String;)Ljava/lang/StringBuilder;
    //   298: pop
    //   299: aload 4
    //   301: astore_2
    //   302: aload 6
    //   304: ldc 18
    //   306: aload 7
    //   308: invokevirtual 101	java/lang/StringBuilder:toString	()Ljava/lang/String;
    //   311: aload 5
    //   313: invokevirtual 119	com/google/android/gms/common/internal/GmsLogger:e	(Ljava/lang/String;Ljava/lang/String;Ljava/lang/Throwable;)V
    //   316: aload 4
    //   318: ifnull +8 -> 326
    //   321: aload 4
    //   323: invokestatic 115	com/google/android/gms/common/util/IOUtils:closeQuietly	(Ljava/io/Closeable;)V
    //   326: aload_3
    //   327: astore_2
    //   328: aload_2
    //   329: astore_3
    //   330: aload_2
    //   331: ifnonnull +16 -> 347
    //   334: getstatic 26	com/google/android/gms/common/internal/LibraryVersion:zza	Lcom/google/android/gms/common/internal/GmsLogger;
    //   337: ldc 18
    //   339: ldc 121
    //   341: invokevirtual 124	com/google/android/gms/common/internal/GmsLogger:d	(Ljava/lang/String;Ljava/lang/String;)V
    //   344: ldc 126
    //   346: astore_3
    //   347: aload_0
    //   348: getfield 38	com/google/android/gms/common/internal/LibraryVersion:zzc	Ljava/util/concurrent/ConcurrentHashMap;
    //   351: aload_1
    //   352: aload_3
    //   353: invokevirtual 130	java/util/concurrent/ConcurrentHashMap:put	(Ljava/lang/Object;Ljava/lang/Object;)Ljava/lang/Object;
    //   356: pop
    //   357: aload_3
    //   358: areturn
    //   359: aload_2
    //   360: ifnull +7 -> 367
    //   363: aload_2
    //   364: invokestatic 115	com/google/android/gms/common/util/IOUtils:closeQuietly	(Ljava/io/Closeable;)V
    //   367: aload_1
    //   368: athrow
    // Local variable table:
    //   start	length	slot	name	signature
    //   0	369	0	this	LibraryVersion
    //   0	369	1	paramString	String
    //   43	321	2	localObject1	Object
    //   48	310	3	localObject2	Object
    //   67	255	4	localObject3	Object
    //   40	161	5	localGmsLogger	GmsLogger
    //   239	1	5	localIOException1	java.io.IOException
    //   250	62	5	localIOException2	java.io.IOException
    //   45	258	6	localObject4	Object
    //   37	270	7	localObject5	Object
    // Exception table:
    //   from	to	target	type
    //   77	84	232	finally
    //   87	96	232	finally
    //   98	103	232	finally
    //   105	114	232	finally
    //   116	123	232	finally
    //   125	133	232	finally
    //   135	142	232	finally
    //   144	156	232	finally
    //   162	167	232	finally
    //   170	179	232	finally
    //   182	190	232	finally
    //   193	200	232	finally
    //   203	215	232	finally
    //   77	84	239	java/io/IOException
    //   87	96	239	java/io/IOException
    //   98	103	239	java/io/IOException
    //   105	114	239	java/io/IOException
    //   116	123	239	java/io/IOException
    //   125	133	239	java/io/IOException
    //   135	142	239	java/io/IOException
    //   144	156	239	java/io/IOException
    //   162	167	239	java/io/IOException
    //   170	179	239	java/io/IOException
    //   182	190	239	java/io/IOException
    //   193	200	239	java/io/IOException
    //   203	215	239	java/io/IOException
    //   49	69	246	finally
    //   261	266	246	finally
    //   269	278	246	finally
    //   281	289	246	finally
    //   292	299	246	finally
    //   302	316	246	finally
    //   49	69	250	java/io/IOException
  }
}
