package com.google.android.gms.common.api.internal;

abstract class zaav
  implements Runnable
{
  /* Error */
  public final void run()
  {
    // Byte code:
    //   0: aload_0
    //   1: getfield 12	com/google/android/gms/common/api/internal/zaav:zab	Lcom/google/android/gms/common/api/internal/zaaw;
    //   4: invokestatic 25	com/google/android/gms/common/api/internal/zaaw:zap	(Lcom/google/android/gms/common/api/internal/zaaw;)Ljava/util/concurrent/locks/Lock;
    //   7: invokeinterface 30 1 0
    //   12: invokestatic 36	java/lang/Thread:interrupted	()Z
    //   15: istore_1
    //   16: iload_1
    //   17: ifeq +18 -> 35
    //   20: aload_0
    //   21: getfield 12	com/google/android/gms/common/api/internal/zaav:zab	Lcom/google/android/gms/common/api/internal/zaaw;
    //   24: invokestatic 25	com/google/android/gms/common/api/internal/zaaw:zap	(Lcom/google/android/gms/common/api/internal/zaaw;)Ljava/util/concurrent/locks/Lock;
    //   27: astore_2
    //   28: aload_2
    //   29: invokeinterface 39 1 0
    //   34: return
    //   35: aload_0
    //   36: invokevirtual 42	com/google/android/gms/common/api/internal/zaav:zaa	()V
    //   39: aload_0
    //   40: getfield 12	com/google/android/gms/common/api/internal/zaav:zab	Lcom/google/android/gms/common/api/internal/zaaw;
    //   43: invokestatic 25	com/google/android/gms/common/api/internal/zaaw:zap	(Lcom/google/android/gms/common/api/internal/zaaw;)Ljava/util/concurrent/locks/Lock;
    //   46: astore_2
    //   47: goto -19 -> 28
    //   50: astore_2
    //   51: goto +26 -> 77
    //   54: astore_2
    //   55: aload_0
    //   56: getfield 12	com/google/android/gms/common/api/internal/zaav:zab	Lcom/google/android/gms/common/api/internal/zaaw;
    //   59: invokestatic 46	com/google/android/gms/common/api/internal/zaaw:zak	(Lcom/google/android/gms/common/api/internal/zaaw;)Lcom/google/android/gms/common/api/internal/zabi;
    //   62: aload_2
    //   63: invokevirtual 52	com/google/android/gms/common/api/internal/zabi:zam	(Ljava/lang/RuntimeException;)V
    //   66: aload_0
    //   67: getfield 12	com/google/android/gms/common/api/internal/zaav:zab	Lcom/google/android/gms/common/api/internal/zaaw;
    //   70: invokestatic 25	com/google/android/gms/common/api/internal/zaaw:zap	(Lcom/google/android/gms/common/api/internal/zaaw;)Ljava/util/concurrent/locks/Lock;
    //   73: astore_2
    //   74: goto -46 -> 28
    //   77: aload_0
    //   78: getfield 12	com/google/android/gms/common/api/internal/zaav:zab	Lcom/google/android/gms/common/api/internal/zaaw;
    //   81: invokestatic 25	com/google/android/gms/common/api/internal/zaaw:zap	(Lcom/google/android/gms/common/api/internal/zaaw;)Ljava/util/concurrent/locks/Lock;
    //   84: invokeinterface 39 1 0
    //   89: aload_2
    //   90: athrow
    // Local variable table:
    //   start	length	slot	name	signature
    //   0	91	0	this	zaav
    //   15	2	1	bool	boolean
    //   27	20	2	localLock1	java.util.concurrent.locks.Lock
    //   50	1	2	localObject	Object
    //   54	9	2	localRuntimeException	RuntimeException
    //   73	17	2	localLock2	java.util.concurrent.locks.Lock
    // Exception table:
    //   from	to	target	type
    //   12	16	50	finally
    //   35	39	50	finally
    //   55	66	50	finally
    //   12	16	54	java/lang/RuntimeException
    //   35	39	54	java/lang/RuntimeException
  }
  
  protected abstract void zaa();
}
