package androidx.activity;

import android.app.Activity;
import android.view.inputmethod.InputMethodManager;
import androidx.lifecycle.k;
import java.lang.reflect.Field;

final class ImmLeaksCleaner
  implements k
{
  private static int a;
  private static Field b;
  private static Field c;
  private static Field d;
  private Activity e;
  
  ImmLeaksCleaner(Activity paramActivity)
  {
    e = paramActivity;
  }
  
  private static void h()
  {
    try
    {
      a = 2;
      Field localField = InputMethodManager.class.getDeclaredField("mServedView");
      c = localField;
      localField.setAccessible(true);
      localField = InputMethodManager.class.getDeclaredField("mNextServedView");
      d = localField;
      localField.setAccessible(true);
      localField = InputMethodManager.class.getDeclaredField("mH");
      b = localField;
      localField.setAccessible(true);
      a = 1;
      return;
    }
    catch (NoSuchFieldException localNoSuchFieldException) {}
  }
  
  /* Error */
  public void c(androidx.lifecycle.m paramM, androidx.lifecycle.Lifecycle.Event paramEvent)
  {
    // Byte code:
    //   0: aload_2
    //   1: getstatic 65	androidx/lifecycle/Lifecycle$Event:ON_DESTROY	Landroidx/lifecycle/Lifecycle$Event;
    //   4: if_acmpeq +4 -> 8
    //   7: return
    //   8: getstatic 28	androidx/activity/ImmLeaksCleaner:a	I
    //   11: ifne +6 -> 17
    //   14: invokestatic 67	androidx/activity/ImmLeaksCleaner:h	()V
    //   17: getstatic 28	androidx/activity/ImmLeaksCleaner:a	I
    //   20: iconst_1
    //   21: if_icmpne +88 -> 109
    //   24: aload_0
    //   25: getfield 23	androidx/activity/ImmLeaksCleaner:e	Landroid/app/Activity;
    //   28: ldc 69
    //   30: invokevirtual 75	android/app/Activity:getSystemService	(Ljava/lang/String;)Ljava/lang/Object;
    //   33: checkcast 30	android/view/inputmethod/InputMethodManager
    //   36: astore_2
    //   37: getstatic 54	androidx/activity/ImmLeaksCleaner:b	Ljava/lang/reflect/Field;
    //   40: aload_2
    //   41: invokevirtual 79	java/lang/reflect/Field:get	(Ljava/lang/Object;)Ljava/lang/Object;
    //   44: astore_1
    //   45: aload_1
    //   46: ifnonnull +4 -> 50
    //   49: return
    //   50: aload_1
    //   51: monitorenter
    //   52: getstatic 40	androidx/activity/ImmLeaksCleaner:c	Ljava/lang/reflect/Field;
    //   55: aload_2
    //   56: invokevirtual 79	java/lang/reflect/Field:get	(Ljava/lang/Object;)Ljava/lang/Object;
    //   59: checkcast 81	android/view/View
    //   62: astore_3
    //   63: aload_3
    //   64: ifnonnull +6 -> 70
    //   67: aload_1
    //   68: monitorexit
    //   69: return
    //   70: aload_3
    //   71: invokevirtual 85	android/view/View:isAttachedToWindow	()Z
    //   74: ifeq +6 -> 80
    //   77: aload_1
    //   78: monitorexit
    //   79: return
    //   80: getstatic 50	androidx/activity/ImmLeaksCleaner:d	Ljava/lang/reflect/Field;
    //   83: aload_2
    //   84: aconst_null
    //   85: invokevirtual 89	java/lang/reflect/Field:set	(Ljava/lang/Object;Ljava/lang/Object;)V
    //   88: aload_1
    //   89: monitorexit
    //   90: aload_2
    //   91: invokevirtual 92	android/view/inputmethod/InputMethodManager:isActive	()Z
    //   94: pop
    //   95: return
    //   96: aload_1
    //   97: monitorexit
    //   98: return
    //   99: aload_1
    //   100: monitorexit
    //   101: return
    //   102: aload_1
    //   103: monitorexit
    //   104: return
    //   105: aload_1
    //   106: monitorexit
    //   107: aload_2
    //   108: athrow
    //   109: return
    //   110: astore_1
    //   111: return
    //   112: astore_2
    //   113: goto -11 -> 102
    //   116: astore_2
    //   117: goto -18 -> 99
    //   120: astore_2
    //   121: goto -25 -> 96
    //   124: astore_2
    //   125: goto -20 -> 105
    // Local variable table:
    //   start	length	slot	name	signature
    //   0	128	0	this	ImmLeaksCleaner
    //   0	128	1	paramM	androidx.lifecycle.m
    //   0	128	2	paramEvent	androidx.lifecycle.Lifecycle.Event
    //   62	9	3	localView	android.view.View
    // Exception table:
    //   from	to	target	type
    //   37	45	110	java/lang/IllegalAccessException
    //   52	63	112	java/lang/IllegalAccessException
    //   52	63	116	java/lang/ClassCastException
    //   80	88	120	java/lang/IllegalAccessException
    //   52	63	124	finally
    //   67	69	124	finally
    //   70	79	124	finally
    //   80	88	124	finally
    //   88	90	124	finally
    //   96	98	124	finally
    //   99	101	124	finally
    //   102	104	124	finally
    //   105	107	124	finally
  }
}
