package com.google.android.gms.common.config;

import com.google.android.gms.common.annotation.KeepForSdk;
import com.google.android.gms.common.util.VisibleForTesting;

@KeepForSdk
public abstract class GservicesValue<T>
{
  private static final Object zzc = new Object();
  protected final String zza;
  protected final Object zzb;
  private Object zzd = null;
  
  protected GservicesValue(String paramString, Object paramObject)
  {
    zza = paramString;
    zzb = paramObject;
  }
  
  @KeepForSdk
  public static boolean isInitialized()
  {
    synchronized (zzc)
    {
      return false;
    }
  }
  
  @KeepForSdk
  public static GservicesValue<Float> value(String paramString, Float paramFloat)
  {
    return new zzd(paramString, paramFloat);
  }
  
  @KeepForSdk
  public static GservicesValue<Integer> value(String paramString, Integer paramInteger)
  {
    return new zzc(paramString, paramInteger);
  }
  
  @KeepForSdk
  public static GservicesValue<Long> value(String paramString, Long paramLong)
  {
    return new zzb(paramString, paramLong);
  }
  
  @KeepForSdk
  public static GservicesValue<String> value(String paramString1, String paramString2)
  {
    return new zze(paramString1, paramString2);
  }
  
  @KeepForSdk
  public static GservicesValue<Boolean> value(String paramString, boolean paramBoolean)
  {
    return new zza(paramString, Boolean.valueOf(paramBoolean));
  }
  
  /* Error */
  @KeepForSdk
  public final T get()
  {
    // Byte code:
    //   0: aload_0
    //   1: getfield 23	com/google/android/gms/common/config/GservicesValue:zzd	Ljava/lang/Object;
    //   4: astore_3
    //   5: aload_3
    //   6: ifnull +5 -> 11
    //   9: aload_3
    //   10: areturn
    //   11: invokestatic 83	android/os/StrictMode:allowThreadDiskReads	()Landroid/os/StrictMode$ThreadPolicy;
    //   14: astore_3
    //   15: getstatic 19	com/google/android/gms/common/config/GservicesValue:zzc	Ljava/lang/Object;
    //   18: astore 4
    //   20: aload 4
    //   22: monitorenter
    //   23: aload 4
    //   25: monitorexit
    //   26: aload 4
    //   28: monitorenter
    //   29: aload 4
    //   31: monitorexit
    //   32: aload_0
    //   33: aload_0
    //   34: getfield 25	com/google/android/gms/common/config/GservicesValue:zza	Ljava/lang/String;
    //   37: invokevirtual 86	com/google/android/gms/common/config/GservicesValue:zza	(Ljava/lang/String;)Ljava/lang/Object;
    //   40: astore 4
    //   42: aload_3
    //   43: invokestatic 90	android/os/StrictMode:setThreadPolicy	(Landroid/os/StrictMode$ThreadPolicy;)V
    //   46: aload 4
    //   48: areturn
    //   49: astore 4
    //   51: goto +37 -> 88
    //   54: invokestatic 96	android/os/Binder:clearCallingIdentity	()J
    //   57: lstore_1
    //   58: aload_0
    //   59: aload_0
    //   60: getfield 25	com/google/android/gms/common/config/GservicesValue:zza	Ljava/lang/String;
    //   63: invokevirtual 86	com/google/android/gms/common/config/GservicesValue:zza	(Ljava/lang/String;)Ljava/lang/Object;
    //   66: astore 4
    //   68: lload_1
    //   69: invokestatic 100	android/os/Binder:restoreCallingIdentity	(J)V
    //   72: aload_3
    //   73: invokestatic 90	android/os/StrictMode:setThreadPolicy	(Landroid/os/StrictMode$ThreadPolicy;)V
    //   76: aload 4
    //   78: areturn
    //   79: astore 4
    //   81: lload_1
    //   82: invokestatic 100	android/os/Binder:restoreCallingIdentity	(J)V
    //   85: aload 4
    //   87: athrow
    //   88: aload_3
    //   89: invokestatic 90	android/os/StrictMode:setThreadPolicy	(Landroid/os/StrictMode$ThreadPolicy;)V
    //   92: aload 4
    //   94: athrow
    //   95: astore_3
    //   96: aload 4
    //   98: monitorexit
    //   99: aload_3
    //   100: athrow
    //   101: astore_3
    //   102: aload 4
    //   104: monitorexit
    //   105: aload_3
    //   106: athrow
    //   107: astore 4
    //   109: goto -55 -> 54
    // Local variable table:
    //   start	length	slot	name	signature
    //   0	112	0	this	GservicesValue
    //   57	25	1	l	long
    //   4	85	3	localObject1	Object
    //   95	5	3	localObject2	Object
    //   101	5	3	localObject3	Object
    //   18	29	4	localObject4	Object
    //   49	1	4	localObject5	Object
    //   66	11	4	localObject6	Object
    //   79	24	4	localObject7	Object
    //   107	1	4	localSecurityException	SecurityException
    // Exception table:
    //   from	to	target	type
    //   32	42	49	finally
    //   54	58	49	finally
    //   68	72	49	finally
    //   81	88	49	finally
    //   58	68	79	finally
    //   29	32	95	finally
    //   96	99	95	finally
    //   23	26	101	finally
    //   102	105	101	finally
    //   32	42	107	java/lang/SecurityException
  }
  
  @Deprecated
  @KeepForSdk
  public final T getBinderSafe()
  {
    return get();
  }
  
  /* Error */
  @KeepForSdk
  @VisibleForTesting
  public void override(T paramT)
  {
    // Byte code:
    //   0: ldc 111
    //   2: ldc 113
    //   4: invokestatic 119	android/util/Log:w	(Ljava/lang/String;Ljava/lang/String;)I
    //   7: pop
    //   8: aload_0
    //   9: aload_1
    //   10: putfield 23	com/google/android/gms/common/config/GservicesValue:zzd	Ljava/lang/Object;
    //   13: getstatic 19	com/google/android/gms/common/config/GservicesValue:zzc	Ljava/lang/Object;
    //   16: astore_1
    //   17: aload_1
    //   18: monitorenter
    //   19: aload_1
    //   20: monitorenter
    //   21: aload_1
    //   22: monitorexit
    //   23: aload_1
    //   24: monitorexit
    //   25: return
    //   26: astore_2
    //   27: aload_1
    //   28: monitorexit
    //   29: aload_2
    //   30: athrow
    //   31: astore_2
    //   32: aload_1
    //   33: monitorexit
    //   34: aload_2
    //   35: athrow
    // Local variable table:
    //   start	length	slot	name	signature
    //   0	36	0	this	GservicesValue
    //   0	36	1	paramT	T
    //   26	4	2	localObject1	Object
    //   31	4	2	localObject2	Object
    // Exception table:
    //   from	to	target	type
    //   21	23	26	finally
    //   27	29	26	finally
    //   19	21	31	finally
    //   23	25	31	finally
    //   29	31	31	finally
    //   32	34	31	finally
  }
  
  @KeepForSdk
  @VisibleForTesting
  public void resetOverride()
  {
    zzd = null;
  }
  
  protected abstract Object zza(String paramString);
}
